fawn.py
fawn-2.1.1.dist-info/DESCRIPTION.rst
fawn-2.1.1.dist-info/METADATA
fawn-2.1.1.dist-info/RECORD
fawn-2.1.1.dist-info/WHEEL
fawn-2.1.1.dist-info/metadata.json
fawn-2.1.1.dist-info/top_level.txt
