Metadata-Version: 2.0
Name: fawn
Version: 2.1.1
Summary: flask async uwsgi websocket postgresql notify
Home-page: https://github.com/paradoxxxzero/fawn
Author: Florian Mounier
Author-email: paradoxxx.zero@gmail.com
License: MIT
Keywords: flask,async,uwsgi,websocket,postgresql,notify
Platform: Any
Classifier: Development Status :: 4 - Beta
Classifier: Intended Audience :: Developers
Classifier: License :: OSI Approved :: MIT License
Classifier: Operating System :: OS Independent
Classifier: Programming Language :: Python :: 2
Classifier: Programming Language :: Python :: 3
Classifier: Topic :: Software Development :: Libraries :: Python Modules
Provides: fawn
Requires-Dist: flask
Requires-Dist: psycopg2
Requires-Dist: sqlalchemy
